{ "height":79,
 "infinite":false,
 "layers":[
        {
         "draworder":"topdown",
         "name":"Object Layer ",
         "objects":[
                {
                 "height":30.7923,
                 "id":33,
                 "name":"entrance",
                 "rotation":0,
                 "type":"",
                 "visible":true,
                 "width":31.6245,
                 "x":128.995,
                 "y":161.451
                }, 
                {
                 "height":31.6245,
                 "id":34,
                 "name":"player",
                 "rotation":0,
                 "type":"",
                 "visible":true,
                 "width":33.2889,
                 "x":255.493,
                 "y":384.487
                }, 
                {
                 "height":32.4567,
                 "id":35,
                 "name":"coral1",
                 "rotation":0,
                 "type":"",
                 "visible":true,
                 "width":33.2889,
                 "x":477.696,
                 "y":414.447
                }, 
                {
                 "height":34.9534,
                 "id":36,
                 "name":"button1",
                 "rotation":0,
                 "type":"",
                 "visible":true,
                 "width":36.6178,
                 "x":699.9,
                 "y":509.321
                }, 
                {
                 "height":40.779,
                 "id":37,
                 "name":"coral2",
                 "rotation":0,
                 "type":"",
                 "visible":true,
                 "width":34.1212,
                 "x":925.433,
                 "y":410.286
                }, 
                {
                 "height":32.4567,
                 "id":38,
                 "name":"hammerHead",
                 "rotation":0,
                 "type":"",
                 "visible":true,
                 "width":32.4567,
                 "x":1279.96,
                 "y":382.823
                }, 
                {
                 "height":33.2889,
                 "id":39,
                 "name":"wall2",
                 "rotation":0,
                 "type":"",
                 "visible":true,
                 "width":35.7856,
                 "x":1949.07,
                 "y":381.991
                }, 
                {
                 "height":33.2889,
                 "id":40,
                 "name":"wall1",
                 "rotation":0,
                 "type":"",
                 "visible":true,
                 "width":30.7923,
                 "x":1279.96,
                 "y":863.848
                }, 
                {
                 "height":34.7423,
                 "id":41,
                 "name":"button2",
                 "rotation":0,
                 "type":"",
                 "visible":true,
                 "width":28.9519,
                 "x":2081.64,
                 "y":1152.29
                }, 
                {
                 "height":46.3231,
                 "id":44,
                 "name":"speedBoost",
                 "rotation":0,
                 "type":"",
                 "visible":true,
                 "width":37.6375,
                 "x":2078.75,
                 "y":602.2
                }, 
                {
                 "height":34.7423,
                 "id":45,
                 "name":"coral3",
                 "rotation":0,
                 "type":"",
                 "visible":true,
                 "width":31.8471,
                 "x":2785.18,
                 "y":1085.7
                }, 
                {
                 "height":31.8471,
                 "id":46,
                 "name":"coral4",
                 "rotation":0,
                 "type":"",
                 "visible":true,
                 "width":23.1616,
                 "x":648.523,
                 "y":1088.59
                }, 
                {
                 "height":49.2183,
                 "id":47,
                 "name":"coral5",
                 "rotation":0,
                 "type":"",
                 "visible":true,
                 "width":37.6375,
                 "x":477.707,
                 "y":1077.01
                }, 
                {
                 "height":37.6375,
                 "id":48,
                 "name":"coral6",
                 "rotation":0,
                 "type":"",
                 "visible":true,
                 "width":28.9519,
                 "x":330.052,
                 "y":1088.59
                }, 
                {
                 "height":35.0728,
                 "id":49,
                 "name":"coral7",
                 "rotation":0,
                 "type":"",
                 "visible":true,
                 "width":31.8844,
                 "x":191.306,
                 "y":1085.13
                }, 
                {
                 "height":34.01,
                 "id":50,
                 "name":"heavyBox",
                 "rotation":0,
                 "type":"",
                 "visible":true,
                 "width":35.0728,
                 "x":381.55,
                 "y":1023.49
                }, 
                {
                 "height":33.8083,
                 "id":51,
                 "name":"clownFish",
                 "rotation":0,
                 "type":"",
                 "visible":true,
                 "width":33.8083,
                 "x":2209.61,
                 "y":1410.29
                }, 
                {
                 "height":38.638,
                 "id":52,
                 "name":"coral8",
                 "rotation":0,
                 "type":"",
                 "visible":true,
                 "width":36.2231,
                 "x":2018.84,
                 "y":1371.65
                }, 
                {
                 "height":35.4448,
                 "id":53,
                 "name":"button3",
                 "rotation":0,
                 "type":"",
                 "visible":true,
                 "width":30.8713,
                 "x":2881.32,
                 "y":1757.37
                }, 
                {
                 "height":36.1827,
                 "id":54,
                 "name":"wall3",
                 "rotation":0,
                 "type":"",
                 "visible":true,
                 "width":29.3985,
                 "x":2369.97,
                 "y":1662.14
                }, 
                {
                 "height":47.4898,
                 "id":55,
                 "name":"coral9",
                 "rotation":0,
                 "type":"",
                 "visible":true,
                 "width":38.4441,
                 "x":1628.22,
                 "y":1530.98
                }, 
                {
                 "height":32.3067,
                 "id":56,
                 "name":"coral10",
                 "rotation":0,
                 "type":"",
                 "visible":true,
                 "width":34.4605,
                 "x":1214.73,
                 "y":1531.34
                }, 
                {
                 "height":45.2294,
                 "id":57,
                 "name":"coral11",
                 "rotation":0,
                 "type":"",
                 "visible":true,
                 "width":43.0756,
                 "x":792.591,
                 "y":1533.49
                }, 
                {
                 "height":43.0756,
                 "id":58,
                 "name":"ball",
                 "rotation":0,
                 "type":"",
                 "visible":true,
                 "width":38.768,
                 "x":217.532,
                 "y":2043.94
                }, 
                {
                 "height":36.6143,
                 "id":59,
                 "name":"exit",
                 "rotation":0,
                 "type":"",
                 "visible":true,
                 "width":45.2294,
                 "x":2995.91,
                 "y":2108.55
                }, 
                {
                 "height":31.4136,
                 "id":60,
                 "name":"button4",
                 "rotation":0,
                 "type":"",
                 "visible":true,
                 "width":36.6492,
                 "x":2685.86,
                 "y":2115.18
                }],
         "opacity":1,
         "type":"objectgroup",
         "visible":true,
         "x":0,
         "y":0
        }, 
        {
         "data":[0, 0, 0, 0, 0, 0, 0, 0, 0, 0, 0, 0, 0, 0, 0, 0, 0, 0, 0, 0, 0, 0, 0, 0, 0, 0, 0, 0, 0, 0, 0, 0, 0, 0, 0, 0, 0, 0, 0, 0, 0, 0, 0, 0, 0, 0, 2684356805, 2684356735, 2684356665, 2684356595, 2684356525, 2684356455, 2684356385, 2684356315, 2684356245, 2684356175, 2684356105, 2684356805, 2684356735, 2684356665, 2684356805, 2684356735, 2684356665, 2684356595, 2684356525, 2684356455, 2684356385, 2684356315, 2684356245, 2684356175, 2684356105, 1610614284, 1610614354, 1610614424, 1610614494, 1610614564, 1610614634, 1610614704, 1610614774, 1610614844, 1610614914, 1610614984, 1610614284, 1610614354, 1610614424, 1610614494, 1610614564, 1610614634, 1610614704, 1610614774, 1610614284, 1610614354, 1610614424, 1610614494, 1610614564, 1610614634, 1610614704, 1610614774, 1610614844, 1610614914, 0, 0, 0, 0, 0, 0, 0, 0, 0, 0, 0, 0, 0, 0, 0, 0, 0, 0, 0, 0, 0, 0, 0, 0, 0, 0, 0, 0, 0, 0, 0, 0, 0, 0, 0, 0, 0, 0, 0, 0, 0, 0, 0, 0, 0, 0, 2684356806, 2684356736, 2684356666, 2684356596, 2684356526, 2684356456, 2684356386, 2684356316, 2684356246, 2684356176, 2684356106, 2684356806, 2684356736, 2684356666, 2684356806, 2684356736, 2684356666, 2684356596, 2684356526, 2684356456, 2684356386, 2684356316, 2684356246, 2684356176, 2684356106, 1610614283, 1610614353, 1610614423, 1610614493, 1610614563, 1610614633, 1610614703, 1610614773, 1610614843, 1610614913, 1610614983, 1610614283, 1610614353, 1610614423, 1610614493, 1610614563, 1610614633, 1610614703, 1610614773, 1610614283, 1610614353, 1610614423, 1610614493, 1610614563, 1610614633, 1610614703, 1610614773, 1610614843, 1610614913, 0, 0, 0, 0, 0, 0, 0, 0, 0, 0, 0, 0, 0, 0, 0, 0, 0, 0, 0, 0, 0, 0, 0, 0, 0, 0, 0, 0, 0, 0, 0, 0, 0, 0, 0, 0, 0, 0, 0, 0, 0, 0, 0, 0, 0, 0, 2684356807, 2684356737, 2684356667, 2684356597, 2684356527, 2684356457, 2684356387, 2684356317, 2684356247, 2684356177, 2684356107, 2684356807, 2684356737, 2684356667, 2684356807, 2684356737, 2684356667, 2684356597, 2684356527, 2684356457, 2684356387, 2684356317, 2684356247, 2684356177, 2684356107, 1610614282, 1610614352, 1610614422, 1610614492, 1610614562, 1610614632, 1610614702, 1610614772, 1610614842, 1610614912, 1610614982, 1610614282, 1610614352, 1610614422, 1610614492, 1610614562, 1610614632, 1610614702, 1610614772, 1610614282, 1610614352, 1610614422, 1610614492, 1610614562, 1610614632, 1610614702, 1610614772, 1610614842, 1610614912, 0, 0, 0, 0, 0, 0, 0, 0, 0, 0, 0, 0, 0, 0, 0, 0, 0, 0, 0, 0, 0, 0, 0, 0, 0, 0, 0, 0, 0, 0, 0, 0, 0, 0, 0, 0, 0, 0, 0, 0, 0, 0, 0, 0, 0, 0, 2684356808, 2684356738, 2684356668, 2684356598, 2684356528, 2684356458, 2684356388, 2684356318, 2684356248, 2684356178, 2684356108, 2684356808, 2684356738, 2684356668, 2684356808, 2684356738, 2684356668, 2684356598, 2684356528, 2684356458, 2684356388, 2684356318, 2684356248, 2684356178, 2684356108, 1610614281, 1610614351, 1610614421, 1610614491, 1610614561, 1610614631, 1610614701, 1610614771, 1610614841, 1610614911, 1610614981, 1610614281, 1610614351, 1610614421, 1610614491, 1610614561, 1610614631, 1610614701, 1610614771, 1610614281, 1610614351, 1610614421, 1610614491, 1610614561, 1610614631, 1610614701, 1610614771, 1610614841, 1610614911, 0, 0, 0, 0, 0, 0, 0, 0, 0, 0, 0, 0, 0, 0, 0, 0, 0, 0, 0, 0, 0, 0, 0, 0, 0, 0, 0, 0, 0, 0, 0, 0, 0, 0, 0, 0, 0, 0, 0, 0, 0, 0, 0, 0, 0, 0, 1610614283, 1610614353, 1610614423, 1610614493, 1610614563, 1610614633, 1610614703, 1610614773, 1610614843, 1610614913, 1610614983, 1610615053, 1610615123, 1610615193, 1610615263, 2684356805, 2684356735, 2684356665, 2684356595, 2684356525, 2684356455, 2684356385, 2684356315, 2684356245, 2684356175, 2684356105, 1610614284, 1610614354, 1610614424, 1610614494, 1610614564, 1610614634, 1610614704, 1610614774, 1610614844, 1610614914, 1610614984, 1610614284, 1610614354, 1610614424, 1610614494, 1610614564, 1610614634, 1610614704, 1610614774, 1610614844, 1610614914, 2684356805, 2684356735, 2684356665, 2684356595, 2684356525, 2684356455, 2684356385, 0, 0, 0, 0, 0, 0, 0, 0, 0, 0, 0, 0, 0, 2684357084, 2684357014, 2684356944, 2684356874, 2684357084, 2684357014, 2684356944, 2684356874, 2684356804, 2684356734, 2684356664, 2684356594, 2684356524, 2684356454, 2684356384, 2684356314, 2684356244, 2684356174, 2684356104, 0, 0, 0, 0, 0, 0, 0, 0, 0, 0, 0, 0, 0, 0, 1610614282, 1610614352, 1610614422, 1610614492, 1610614562, 1610614632, 1610614702, 1610614772, 1610614842, 1610614912, 1610614982, 1610615052, 1610615122, 1610615192, 1610615262, 2684356806, 2684356736, 2684356666, 2684356596, 2684356526, 2684356456, 2684356386, 2684356316, 2684356246, 2684356176, 2684356106, 1610614283, 1610614353, 1610614423, 1610614493, 1610614563, 1610614633, 1610614703, 1610614773, 1610614843, 1610614913, 1610614983, 1610614283, 1610614353, 1610614423, 1610614493, 1610614563, 1610614633, 1610614703, 1610614773, 1610614843, 1610614913, 2684356806, 2684356736, 2684356666, 2684356596, 2684356526, 2684356456, 2684356386, 0, 0, 0, 0, 0, 0, 0, 0, 0, 0, 0, 0, 0, 2684357085, 2684357015, 2684356945, 2684356875, 2684357085, 2684357015, 2684356945, 2684356875, 2684356805, 2684356735, 2684356665, 2684356595, 2684356525, 2684356455, 2684356385, 2684356315, 2684356245, 2684356175, 2684356105, 0, 0, 0, 0, 0, 0, 0, 0, 0, 0, 0, 0, 0, 0, 1610614281, 1610614351, 1610614421, 1610614491, 1610614561, 1610614631, 1610614701, 1610614771, 1610614841, 1610614911, 1610614981, 1610615051, 1610615121, 1610615191, 1610615261, 2684356807, 2684356737, 2684356667, 2684356597, 2684356527, 2684356457, 2684356387, 2684356317, 2684356247, 2684356177, 2684356107, 1610614282, 1610614352, 1610614422, 1610614492, 1610614562, 1610614632, 1610614702, 1610614772, 1610614842, 1610614912, 1610614982, 1610614282, 1610614352, 1610614422, 1610614492, 1610614562, 1610614632, 1610614702, 1610614772, 1610614842, 1610614912, 2684356807, 2684356737, 2684356667, 2684356597, 2684356527, 2684356457, 2684356387, 0, 0, 0, 0, 0, 0, 0, 0, 0, 0, 0, 0, 0, 2684357086, 2684357016, 2684356946, 2684356876, 2684357086, 2684357016, 2684356946, 2684356876, 2684356806, 2684356736, 2684356666, 2684356596, 2684356526, 2684356456, 2684356386, 2684356316, 2684356246, 2684356176, 2684356106, 0, 0, 0, 0, 0, 0, 0, 0, 0, 0, 0, 0, 0, 0, 1610614280, 1610614350, 1610614420, 1610614490, 2387, 2387, 2387, 1610614770, 1610614840, 1610614910, 1610614980, 1610615050, 1610615120, 1610615190, 1610615260, 2684356808, 2684356738, 2684356668, 2684356598, 2684356528, 2684356458, 2684356388, 2684356318, 2684356248, 2684356178, 2684356108, 1610614281, 1610614351, 1610614421, 1610614491, 1610614561, 1610614631, 1610614701, 1610614771, 1610614841, 1610614911, 1610614981, 1610614281, 1610614351, 1610614421, 1610614491, 1610614561, 1610614631, 1610614701, 1610614771, 1610614841, 1610614911, 2684356808, 2684356738, 2684356668, 2684356598, 2684356528, 2684356458, 2684356388, 0, 0, 0, 0, 0, 0, 0, 0, 0, 0, 0, 0, 0, 2684357087, 2684357017, 2684356947, 2684356877, 2684357087, 2684357017, 2684356947, 2684356877, 2684356807, 2684356737, 2684356667, 2684356597, 2684356527, 2684356457, 2684356387, 2684356317, 2684356247, 2684356177, 2684356107, 0, 0, 0, 0, 0, 0, 0, 0, 0, 0, 0, 0, 0, 0, 0, 0, 0, 0, 0, 0, 0, 0, 0, 0, 0, 0, 0, 0, 0, 0, 0, 0, 0, 0, 0, 0, 0, 0, 0, 0, 0, 0, 0, 0, 0, 0, 0, 0, 0, 0, 0, 0, 0, 0, 0, 0, 0, 0, 0, 0, 0, 0, 0, 0, 0, 0, 0, 0, 0, 0, 0, 0, 0, 0, 0, 0, 0, 0, 0, 0, 0, 0, 0, 0, 0, 0, 0, 0, 0, 0, 0, 0, 0, 0, 0, 0, 0, 0, 0, 0, 0, 0, 0, 0, 0, 0, 0, 0, 0, 0, 0, 0, 0, 0, 0, 0, 0, 0, 0, 0, 0, 0, 0, 0, 0, 0, 0, 0, 0, 0, 0, 0, 0, 0, 0, 0, 0, 0, 0, 0, 0, 0, 0, 0, 0, 0, 0, 0, 0, 0, 0, 0, 0, 0, 0, 0, 0, 0, 0, 0, 0, 0, 0, 0, 0, 0, 0, 0, 0, 0, 0, 0, 0, 0, 0, 0, 0, 0, 0, 0, 0, 0, 0, 0, 0, 0, 0, 0, 0, 0, 0, 0, 0, 0, 0, 0, 0, 0, 0, 0, 0, 0, 0, 0, 0, 0, 0, 0, 0, 0, 0, 0, 0, 0, 0, 0, 0, 0, 0, 0, 0, 0, 0, 0, 0, 0, 0, 0, 0, 0, 0, 0, 0, 0, 0, 0, 0, 0, 0, 0, 0, 0, 0, 0, 0, 0, 0, 0, 0, 0, 0, 0, 0, 0, 0, 0, 0, 0, 0, 0, 0, 0, 0, 0, 0, 0, 0, 0, 0, 0, 0, 0, 0, 0, 0, 0, 0, 0, 0, 0, 0, 0, 0, 0, 0, 0, 0, 0, 0, 0, 0, 0, 0, 0, 0, 0, 0, 0, 0, 0, 0, 0, 0, 0, 0, 0, 0, 0, 0, 0, 0, 0, 0, 0, 0, 0, 0, 0, 0, 0, 0, 0, 0, 0, 0, 0, 0, 0, 0, 0, 0, 0, 0, 0, 0, 0, 0, 0, 0, 0, 0, 0, 0, 0, 0, 0, 0, 0, 0, 0, 0, 0, 0, 0, 0, 0, 0, 0, 0, 0, 0, 0, 0, 0, 0, 0, 0, 0, 0, 0, 0, 0, 0, 0, 0, 0, 0, 0, 0, 0, 0, 0, 0, 0, 0, 0, 0, 0, 0, 0, 0, 0, 0, 0, 0, 0, 0, 0, 0, 0, 0, 0, 0, 0, 0, 0, 0, 0, 0, 0, 0, 0, 0, 0, 0, 0, 0, 0, 0, 0, 0, 0, 0, 0, 0, 0, 0, 0, 0, 0, 0, 0, 0, 0, 0, 0, 0, 0, 0, 0, 0, 0, 0, 0, 0, 0, 0, 0, 0, 0, 0, 0, 0, 0, 0, 0, 0, 0, 0, 0, 0, 0, 0, 0, 0, 0, 0, 0, 0, 0, 0, 0, 0, 0, 0, 0, 0, 0, 0, 0, 0, 0, 0, 0, 0, 0, 0, 0, 0, 0, 0, 0, 0, 0, 0, 0, 0, 0, 0, 0, 0, 0, 0, 0, 0, 0, 0, 0, 0, 0, 0, 0, 0, 0, 0, 0, 0, 0, 0, 0, 0, 0, 0, 0, 0, 0, 0, 0, 0, 0, 0, 0, 0, 0, 0, 0, 0, 0, 0, 0, 0, 0, 0, 0, 0, 0, 0, 0, 0, 0, 0, 0, 0, 0, 0, 0, 0, 0, 0, 0, 0, 0, 0, 0, 0, 0, 0, 0, 0, 0, 0, 0, 0, 0, 0, 0, 0, 0, 0, 0, 0, 0, 0, 0, 0, 0, 0, 0, 0, 0, 0, 0, 0, 0, 0, 0, 0, 0, 0, 0, 0, 0, 0, 0, 0, 0, 0, 0, 0, 0, 0, 0, 0, 0, 0, 0, 0, 0, 0, 0, 0, 0, 0, 0, 0, 0, 0, 0, 0, 0, 0, 0, 0, 0, 0, 0, 0, 0, 0, 0, 0, 0, 0, 0, 0, 0, 0, 0, 0, 0, 0, 0, 0, 0, 0, 0, 0, 0, 0, 0, 0, 0, 0, 0, 0, 0, 0, 0, 0, 0, 0, 0, 0, 0, 0, 0, 0, 0, 0, 0, 0, 0, 0, 0, 0, 0, 0, 0, 0, 0, 0, 0, 0, 0, 0, 0, 0, 0, 0, 0, 0, 0, 0, 0, 0, 0, 0, 0, 0, 0, 0, 0, 0, 0, 0, 0, 0, 0, 0, 0, 0, 0, 0, 0, 0, 0, 0, 0, 0, 0, 0, 0, 0, 0, 0, 0, 0, 0, 0, 0, 0, 0, 0, 0, 0, 0, 0, 0, 0, 0, 0, 0, 0, 0, 0, 0, 0, 0, 0, 0, 0, 0, 0, 0, 0, 0, 0, 0, 2684357223, 2684357153, 2684357083, 2684357013, 2684356943, 2684356873, 2684356803, 2684356733, 2684356663, 2684356593, 2684356523, 2684356453, 2684356383, 2684356313, 2684356243, 2684356173, 2684356103, 536872455, 536872525, 536872595, 536872665, 536872735, 536872805, 536872875, 536872945, 536873015, 536873085, 536873155, 536873225, 536873295, 536873365, 536873435, 536873505, 536873575, 0, 0, 0, 0, 0, 0, 0, 0, 0, 0, 0, 0, 0, 0, 0, 0, 0, 0, 0, 0, 0, 0, 0, 0, 0, 0, 0, 0, 0, 0, 0, 0, 0, 0, 0, 0, 0, 0, 0, 0, 0, 0, 0, 0, 0, 0, 0, 0, 0, 0, 0, 0, 0, 0, 0, 0, 0, 0, 0, 0, 0, 0, 0, 0, 0, 0, 2684357224, 2684357154, 2684357084, 2684357014, 2684356944, 2684356874, 2684356804, 2684356734, 2684356664, 2684356594, 2684356524, 2684356454, 2684356384, 2684356314, 2684356244, 2684356174, 2684356104, 536872456, 536872526, 536872596, 536872666, 536872736, 536872806, 536872876, 536872946, 536873016, 536873086, 536873156, 536873226, 536873296, 536873366, 536873436, 536873506, 536873576, 0, 0, 0, 0, 0, 0, 0, 2684356665, 2684356595, 2684356525, 2684356455, 2684356385, 2684356315, 2684356245, 2684356665, 2684356595, 2684356525, 1610614284, 1610614354, 1610614284, 1610614354, 1610614424, 1610614494, 1610614564, 1610614634, 1610614704, 1610614774, 1610614844, 1610614914, 0, 0, 0, 0, 0, 0, 0, 0, 0, 0, 0, 0, 0, 0, 0, 0, 0, 0, 0, 0, 0, 0, 0, 0, 0, 0, 0, 0, 0, 0, 0, 0, 0, 0, 0, 0, 0, 2684357225, 2684357155, 2684357085, 2684357015, 2684356945, 2684356875, 2684356805, 2684356735, 2684356665, 2684356595, 2684356525, 2684356455, 2684356385, 2684356315, 2684356245, 2684356175, 2684356105, 536872457, 536872527, 536872597, 536872667, 536872737, 536872807, 536872877, 536872947, 536873017, 536873087, 536873157, 536873227, 536873297, 536873367, 536873437, 536873507, 536873577, 0, 0, 0, 0, 0, 0, 0, 2684356666, 2684356596, 2684356526, 2684356456, 2684356386, 2684356316, 2684356246, 2684356666, 2684356596, 2684356526, 1610614283, 1610614353, 1610614283, 1610614353, 1610614423, 1610614493, 1610614563, 1610614633, 1610614703, 1610614773, 1610614843, 1610614913, 0, 0, 0, 0, 0, 0, 0, 0, 0, 0, 0, 0, 0, 0, 0, 0, 0, 0, 0, 0, 0, 0, 0, 0, 0, 0, 0, 0, 0, 0, 0, 0, 0, 0, 0, 0, 0, 2684357226, 2684357156, 2684357086, 2684357016, 2684356946, 2684356876, 2684356806, 2684356736, 2684356666, 2684356596, 2684356526, 2684356456, 2684356386, 2684356316, 2684356246, 2684356176, 2684356106, 536872458, 536872528, 536872598, 536872668, 536872738, 536872808, 536872878, 1685, 1686, 1687, 1688, 1686, 1687, 1688, 1686, 1687, 1688, 0, 0, 0, 0, 0, 0, 0, 2684356667, 2684356597, 2684356527, 2684356457, 2684356387, 2684356317, 2684356247, 2684356667, 2684356597, 2684356527, 1610614282, 1610614352, 1610614284, 1610614354, 1610614424, 1610614494, 1610614564, 1610614634, 1610614704, 1610614774, 1610614844, 1610614914, 0, 0, 0, 0, 0, 0, 0, 0, 0, 0, 0, 0, 0, 0, 0, 0, 0, 0, 0, 0, 0, 0, 0, 0, 0, 0, 0, 0, 0, 0, 0, 0, 0, 0, 0, 0, 0, 2684356945, 2684356875, 2684356805, 2684356735, 2684356665, 2684356595, 2684356525, 2684356455, 2684356385, 2684356315, 2684356245, 536872597, 536872667, 536872737, 536872597, 536872667, 536872737, 536872807, 536872877, 536872947, 536873017, 536873087, 536873157, 536873227, 1755, 1756, 1757, 1758, 1756, 1757, 1758, 1756, 1757, 1758, 0, 0, 0, 0, 0, 0, 0, 2684356668, 2684356598, 2684356528, 2684356458, 2684356388, 2684356318, 2684356248, 2684356668, 2684356598, 2684356528, 1610614284, 1610614354, 1610614283, 1610614353, 1610614423, 1610614493, 1610614563, 1610614633, 1610614703, 1610614773, 1610614843, 1610614913, 0, 0, 0, 0, 0, 0, 0, 0, 0, 0, 0, 0, 0, 0, 0, 0, 0, 0, 0, 0, 0, 0, 0, 0, 0, 0, 0, 0, 0, 0, 0, 0, 0, 0, 0, 0, 0, 2684356946, 2684356876, 2684356806, 2684356736, 2684356666, 2684356596, 2684356526, 2684356456, 2684356386, 2684356316, 2684356246, 536872598, 536872668, 536872738, 536872598, 536872668, 536872738, 536872808, 536872878, 536872948, 536873018, 536873088, 536873158, 536873228, 1825, 1826, 1827, 1828, 1826, 1827, 1828, 1826, 1827, 1828, 0, 0, 0, 0, 0, 0, 0, 1967, 1967, 1967, 1967, 1967, 1967, 1967, 1967, 1967, 1967, 1610614283, 1610614353, 1610614282, 1610614352, 1610614422, 1610614492, 1610614562, 1610614632, 1610614702, 1610614772, 1610614842, 1610614912, 0, 0, 0, 0, 0, 0, 0, 0, 0, 0, 0, 0, 0, 0, 0, 0, 0, 0, 0, 0, 0, 0, 0, 0, 0, 0, 0, 0, 0, 0, 0, 0, 0, 0, 0, 0, 0, 2684356945, 2684356875, 2684356805, 2684356735, 2684356665, 2684356595, 2684356525, 2684356455, 2684356385, 2684356945, 2684356875, 2684356805, 2684356735, 2684356665, 2684356595, 2684356525, 2684356455, 2684356385, 2684356315, 2684356245, 2684356525, 2684356455, 2684356385, 2684356315, 1895, 1896, 1897, 1898, 1896, 1897, 1898, 1896, 1897, 1898, 0, 0, 0, 0, 0, 0, 0, 0, 0, 0, 2684356665, 2684356595, 2684356525, 2684356455, 2684356385, 2684356315, 2684356736, 1610614282, 1610614352, 1610614422, 1610614492, 1610614562, 1610614632, 1610614702, 1610614772, 1610614842, 1610614912, 0, 0, 0, 0, 0, 0, 0, 3650, 3651, 3652, 3653, 0, 0, 0, 0, 0, 0, 0, 0, 0, 0, 1610614284, 1610614354, 1610614424, 1610614494, 0, 0, 0, 0, 0, 0, 0, 0, 0, 0, 0, 0, 0, 0, 2684356946, 2684356876, 2684356806, 2684356736, 2684356666, 2684356596, 2684356526, 2684356456, 2684356386, 2684356946, 2684356876, 2684356806, 2684356736, 2684356666, 2684356596, 2684356526, 2684356456, 2684356386, 2684356316, 2684356246, 2684356526, 2684356456, 2684356386, 2684356316, 1685, 1686, 1687, 1688, 1966, 1967, 1968, 1966, 1967, 1968, 0, 0, 0, 0, 0, 0, 0, 0, 0, 0, 2684356666, 2684356596, 2684356526, 2684356456, 2684356386, 2684356316, 2684356737, 2684356736, 2684356666, 2684356596, 2684356526, 2684356456, 2684356386, 2684356316, 2684356246, 2684356176, 2684356106, 0, 0, 0, 0, 0, 0, 0, 3720, 3721, 3722, 3723, 0, 0, 0, 0, 0, 0, 0, 0, 0, 0, 1610614283, 1610614353, 1610614423, 1610614493, 0, 0, 0, 0, 0, 0, 0, 0, 0, 0, 0, 0, 0, 0, 2684356947, 2684356877, 2684356807, 2684356737, 2684356667, 2684356597, 2684356527, 2684356457, 2684356387, 2684356947, 2684356877, 2684356807, 2684356737, 2684356667, 2684356597, 2684356527, 2684356457, 2684356387, 2684356317, 2684356247, 2684356527, 2684356457, 2684356387, 2684356317, 1755, 1756, 1757, 1758, 2036, 2037, 2038, 2036, 2037, 2038, 0, 0, 0, 0, 0, 0, 0, 0, 0, 0, 2684356667, 2684356597, 2684356527, 2684356457, 2684356387, 2684356317, 2684356738, 2684356737, 2684356667, 2684356597, 2684356527, 2684356457, 2684356387, 2684356317, 2684356247, 2684356177, 2684356107, 0, 0, 0, 0, 0, 0, 0, 3790, 3791, 3792, 3793, 0, 0, 0, 0, 0, 0, 0, 0, 0, 0, 1610614282, 1610614352, 1610614422, 1610614492, 0, 0, 0, 0, 0, 0, 0, 0, 0, 0, 0, 0, 0, 0, 2684356948, 2684356878, 2684356808, 2684356738, 2684356668, 2684356598, 2684356528, 2684356458, 2684356388, 2684356948, 2684356878, 2684356808, 2684356738, 2684356668, 2684356598, 2684356528, 2684356458, 2684356388, 2684356318, 2684356248, 2684356528, 2684356458, 2684356388, 2684356318, 1825, 1826, 1827, 1828, 2106, 2107, 2108, 2106, 2107, 2108, 0, 0, 0, 0, 0, 0, 0, 0, 0, 0, 2684356668, 2684356598, 2684356528, 2684356458, 2684356388, 2684356318, 2684356248, 2684356738, 2684356668, 2684356598, 2684356528, 2684356458, 2684356388, 2684356318, 2684356736, 2684356666, 2684356596, 2684356526, 2684356456, 2684356736, 2684356666, 2684356596, 2684356526, 2684356456, 2684356386, 2684356316, 2684356246, 2684356176, 2684356106, 3221227650, 1610614284, 1610614354, 1610614424, 1610614284, 1610614354, 1610614424, 1610614494, 1610614424, 2684356665, 2684356595, 2684356525, 2684356455, 2684356385, 2684356315, 2684356245, 2684356175, 0, 0, 0, 0, 0, 0, 0, 0, 0, 0, 3221227859, 3221227858, 3221227857, 0, 0, 0, 0, 0, 0, 0, 0, 0, 0, 0, 0, 0, 0, 0, 0, 0, 0, 0, 0, 0, 1895, 1896, 1897, 2684356665, 2684356595, 2684356525, 2684356455, 2684356665, 2684356595, 2684356525, 2684356455, 2684356385, 2684356315, 2684356245, 0, 0, 0, 0, 0, 0, 2684356665, 2684356595, 2684356525, 2684356455, 2684356385, 2684356315, 2684356245, 536872597, 536872667, 536872737, 536872807, 536872877, 536872947, 536873017, 2684356737, 2684356667, 2684356597, 2684356527, 2684356457, 2684356737, 2684356667, 2684356597, 2684356527, 2684356457, 2684356387, 2684356317, 2684356247, 2684356177, 2684356107, 3221227580, 1610614283, 1610614353, 1610614423, 1610614283, 1610614353, 1610614423, 1610614493, 1610614423, 2684356666, 2684356596, 2684356526, 2684356456, 2684356386, 2684356316, 2684356246, 2684356176, 0, 0, 0, 0, 0, 0, 0, 0, 0, 0, 3221227789, 3221227788, 3221227787, 0, 0, 0, 0, 0, 0, 0, 0, 0, 0, 0, 0, 0, 0, 0, 0, 0, 0, 0, 0, 0, 1965, 1966, 1967, 2684356666, 2684356596, 2684356526, 2684356456, 2684356666, 2684356596, 2684356526, 2684356456, 2684356386, 2684356316, 2684356246, 0, 0, 0, 0, 0, 0, 2684356666, 2684356596, 2684356526, 2684356456, 2684356386, 2684356316, 2684356246, 536872598, 536872668, 536872738, 536872808, 536872878, 536872948, 536873018, 2684356738, 2684356668, 2684356598, 2684356528, 2684356458, 2684356738, 2684356668, 2684356598, 2684356528, 2684356458, 2684356388, 2684356318, 2684356248, 2684356178, 2684356108, 3221227510, 1610614282, 1610614352, 1610614422, 1610614282, 1610614352, 1610614422, 1610614492, 1610614422, 2684356667, 2684356597, 2684356527, 2684356457, 2684356387, 2684356317, 2684356247, 2684356177, 0, 0, 0, 0, 0, 0, 0, 0, 0, 0, 3221227719, 3221227718, 3221227717, 0, 0, 0, 0, 0, 0, 0, 0, 0, 0, 0, 0, 0, 0, 0, 0, 0, 0, 0, 0, 0, 2035, 2036, 2037, 2684356667, 2684356597, 2684356527, 2684356457, 2684356667, 2684356597, 2684356527, 2684356457, 2684356387, 2684356317, 2684356247, 0, 0, 0, 0, 0, 0, 2684356667, 2684356597, 2684356527, 2684356457, 2684356387, 2684356317, 2684356247, 536872599, 536872669, 536872739, 536872809, 536872879, 536872949, 536873019, 0, 0, 0, 0, 0, 0, 0, 0, 0, 0, 0, 0, 0, 0, 0, 3221227440, 3221227439, 3221227438, 2684356876, 2684356806, 2684356736, 2684356666, 2684356596, 2684356526, 2684356456, 2684356386, 2684356316, 2684356246, 2684356176, 2684356316, 2684356246, 2684356176, 0, 0, 0, 0, 0, 0, 0, 0, 0, 0, 3221227859, 3221227858, 3221227857, 0, 0, 0, 0, 0, 0, 0, 0, 0, 0, 0, 0, 0, 0, 0, 0, 0, 0, 0, 0, 0, 2105, 2106, 2107, 2684356668, 2684356598, 2684356528, 2684356458, 2684356668, 2684356598, 2684356528, 2684356458, 2684356388, 2684356318, 2684356248, 0, 0, 0, 0, 0, 0, 2684356668, 2684356598, 2684356528, 2684356458, 2684356388, 2684356318, 2684356248, 536872600, 536872670, 536872740, 536872810, 536872880, 536872950, 536873020, 0, 0, 0, 0, 0, 0, 0, 0, 0, 0, 0, 0, 0, 0, 0, 3221227370, 3221227369, 3221227368, 2684356877, 2684356807, 2684356737, 2684356667, 2684356597, 2684356527, 2684356457, 2684356387, 2684356317, 2684356247, 2684356177, 2684356317, 2684356247, 2684356177, 0, 0, 0, 0, 0, 0, 0, 0, 0, 0, 3221227789, 3221227788, 3221227787, 0, 0, 0, 0, 0, 0, 0, 0, 0, 0, 0, 0, 0, 0, 0, 0, 0, 0, 0, 0, 0, 0, 0, 0, 0, 0, 0, 0, 0, 0, 0, 0, 0, 0, 0, 0, 0, 0, 0, 0, 0, 0, 0, 0, 0, 0, 0, 0, 0, 0, 0, 0, 0, 0, 0, 0, 0, 0, 0, 0, 0, 0, 0, 0, 0, 0, 0, 0, 0, 0, 3221227650, 3221227649, 3221227648, 2684356878, 2684356808, 2684356738, 2684356668, 2684356598, 2684356528, 2684356458, 2684356388, 2684356318, 2684356248, 2684356178, 2684356318, 2684356248, 2684356178, 0, 0, 0, 0, 0, 0, 0, 0, 0, 0, 3221227719, 3221227718, 3221227717, 0, 0, 0, 0, 0, 0, 0, 0, 0, 0, 0, 0, 0, 0, 0, 0, 0, 0, 0, 0, 0, 0, 0, 0, 0, 0, 0, 0, 0, 0, 0, 0, 0, 0, 0, 0, 0, 0, 0, 0, 0, 0, 0, 0, 0, 0, 0, 0, 0, 0, 0, 0, 0, 0, 0, 0, 0, 0, 0, 0, 0, 0, 0, 0, 0, 0, 0, 0, 0, 0, 3221227580, 3221227579, 3221227578, 0, 0, 0, 0, 0, 0, 0, 0, 0, 0, 0, 0, 0, 0, 0, 0, 0, 0, 0, 0, 0, 0, 0, 0, 3221227649, 3221227648, 3221227647, 0, 0, 0, 0, 0, 0, 0, 0, 0, 0, 0, 0, 0, 0, 0, 0, 0, 0, 0, 0, 0, 0, 0, 0, 0, 0, 0, 0, 0, 0, 0, 0, 0, 0, 0, 0, 0, 0, 0, 0, 0, 0, 0, 0, 0, 0, 0, 0, 0, 0, 0, 0, 0, 0, 0, 0, 0, 0, 0, 0, 0, 0, 0, 0, 0, 0, 0, 0, 0, 0, 3221227510, 3221227509, 3221227508, 0, 0, 0, 0, 0, 0, 0, 0, 0, 0, 0, 0, 0, 0, 0, 0, 0, 0, 0, 0, 0, 0, 0, 0, 3221227579, 3221227578, 3221227577, 0, 0, 0, 0, 0, 0, 0, 0, 0, 0, 0, 0, 0, 0, 0, 0, 0, 0, 0, 0, 0, 0, 0, 0, 0, 0, 0, 0, 0, 0, 0, 0, 0, 0, 0, 0, 0, 0, 0, 0, 0, 0, 0, 0, 0, 0, 0, 0, 0, 0, 0, 0, 0, 0, 0, 0, 0, 0, 0, 0, 0, 0, 0, 0, 0, 0, 0, 0, 0, 0, 3221227440, 3221227439, 3221227438, 0, 0, 0, 0, 0, 0, 0, 0, 0, 0, 0, 0, 0, 0, 0, 0, 0, 0, 0, 0, 0, 0, 0, 0, 3221227509, 3221227508, 3221227507, 0, 0, 0, 0, 0, 0, 0, 0, 0, 0, 0, 0, 0, 0, 0, 0, 0, 0, 0, 0, 0, 0, 0, 0, 0, 0, 0, 0, 0, 0, 0, 0, 0, 0, 0, 0, 0, 0, 0, 0, 0, 0, 0, 0, 0, 0, 0, 0, 0, 0, 0, 0, 0, 0, 0, 0, 0, 0, 0, 0, 0, 0, 0, 0, 0, 0, 0, 0, 0, 0, 3221227370, 3221227369, 3221227368, 0, 0, 0, 0, 0, 0, 0, 0, 0, 0, 0, 0, 0, 0, 0, 0, 0, 0, 0, 0, 0, 0, 0, 0, 3221227439, 3221227438, 3221227437, 0, 0, 0, 0, 0, 0, 0, 0, 0, 0, 0, 0, 0, 0, 0, 0, 0, 0, 0, 0, 0, 2684356665, 2684356595, 2684356525, 2684356455, 2684356385, 1610614284, 1610614354, 1610614424, 1610614494, 1610614564, 1610614634, 1610614704, 1610614774, 1610614284, 1610614354, 1610614424, 1610614494, 1610614564, 1610614634, 1610614704, 1610614774, 1610614844, 1610614914, 1610614844, 1610614914, 1610614354, 1610614424, 1610614494, 1610614564, 1610614634, 1610614704, 1610614774, 1610614844, 1610614914, 0, 0, 0, 0, 0, 0, 0, 0, 0, 0, 0, 0, 0, 0, 0, 3221227300, 3221227299, 3221227298, 0, 0, 0, 0, 0, 0, 0, 0, 0, 0, 0, 0, 0, 0, 0, 0, 0, 0, 0, 0, 0, 0, 0, 0, 3221227369, 3221227368, 3221227367, 0, 0, 0, 0, 0, 0, 0, 0, 0, 0, 0, 0, 0, 0, 0, 0, 0, 0, 0, 0, 0, 2684356666, 2684356596, 2684356526, 2684356456, 2684356386, 1610614283, 1610614353, 1610614423, 1610614493, 1610614563, 1610614633, 1610614703, 1610614773, 1610614283, 1610614353, 1610614423, 1610614493, 1610614563, 1610614633, 1610614703, 1610614773, 1610614843, 1610614913, 1610614843, 1610614913, 1610614353, 1610614423, 1610614493, 1610614563, 1610614633, 1610614703, 1610614773, 1610614843, 1610614913, 0, 0, 0, 0, 0, 0, 0, 0, 0, 0, 0, 0, 0, 0, 0, 3221227230, 3221227229, 3221227228, 0, 0, 0, 0, 0, 0, 0, 0, 0, 0, 0, 0, 0, 0, 0, 0, 0, 0, 0, 0, 0, 0, 0, 0, 3221227299, 3221227298, 3221227297, 0, 0, 0, 0, 0, 0, 0, 0, 0, 0, 0, 0, 0, 0, 0, 0, 0, 0, 0, 0, 0, 2684356665, 2684356595, 2684356525, 2684356455, 2684356385, 1610614282, 1610614352, 1610614422, 1610614492, 1610614562, 1610614632, 1610614702, 1610614772, 1610614282, 1610614352, 1610614422, 1610614492, 1610614562, 1610614632, 1610614702, 1610614772, 1610614842, 1610614912, 1610614842, 1610614912, 1610614494, 1610614564, 1610614634, 1610614704, 1610614774, 1610614844, 1610614914, 1610614354, 1610614424, 1610614494, 1610614564, 1610614634, 1610614704, 1610614774, 1610614844, 1610614914, 1610614354, 1610614424, 1610614494, 1610614564, 1610614634, 1610614704, 1610614774, 1610614844, 1610614914, 3221227159, 3221227158, 0, 0, 0, 0, 0, 0, 0, 0, 0, 0, 2684356946, 2684356876, 2684356806, 2684356736, 2684356666, 2684356596, 2684356526, 2684356456, 2684356386, 2684356316, 2684356246, 2684356176, 3221227719, 3221227718, 3221227229, 2684357157, 2684357087, 2684357017, 2684356947, 2684356877, 2684356807, 2684356737, 2684356667, 2684356597, 2684356527, 2684357157, 2684357087, 2684357017, 2684356947, 2684356877, 2684356807, 2684356737, 2684356667, 2684356597, 2684356527, 2684356457, 2684356387, 2684356317, 2684356666, 2684356596, 2684356526, 2684356456, 2684356386, 2684356316, 1610614284, 1610614354, 1610614424, 1610614494, 1610614564, 1610614634, 1610614704, 1610614774, 1610614844, 1610614284, 1610614354, 1610614424, 1610614494, 1610614564, 1610614634, 1610614704, 1610614774, 1610614844, 1610614914, 1610614493, 1610614563, 1610614633, 1610614703, 1610614773, 1610614843, 1610614913, 1610614353, 1610614423, 1610614493, 1610614563, 1610614633, 1610614703, 1610614773, 1610614843, 1610614913, 1610614353, 1610614423, 1610614493, 1610614563, 1610614633, 1610614703, 1610614773, 1610614843, 1610614913, 3221227089, 3221227088, 0, 0, 0, 0, 0, 0, 0, 0, 0, 0, 2684356947, 2684356877, 2684356807, 2684356737, 2684356667, 2684356597, 2684356527, 2684356457, 2684356387, 2684356317, 2684356247, 2684356177, 3221227649, 3221227648, 3221228070, 3221228069, 3221228068, 2684356947, 2684356877, 2684356807, 2684356737, 2684356667, 2684356597, 2684356527, 2684356457, 2684356387, 2684356317, 2684356247, 2684356947, 2684356877, 2684356807, 2684356737, 2684356667, 2684356597, 2684356527, 2684356457, 2684356387, 2684356317, 2684356667, 2684356597, 2684356527, 2684356457, 2684356387, 2684356317, 1610614283, 1610614353, 1610614423, 1610614493, 1610614563, 1610614633, 1610614703, 1610614773, 1610614843, 1610614283, 1610614353, 1610614423, 1610614493, 1610614563, 1610614633, 1610614703, 1610614773, 1610614843, 1610614913, 1610614492, 1610614562, 1610614632, 1610614702, 1610614772, 1610614842, 1610614912, 1610614352, 1610614422, 1610614492, 1610614562, 1610614632, 1610614702, 1610614772, 1610614842, 1610614912, 1610614352, 1610614422, 1610614492, 1610614562, 1610614632, 1610614702, 1610614772, 1610614842, 1610614912, 3221227019, 3221227018, 0, 0, 0, 0, 0, 0, 0, 0, 0, 0, 2684356948, 2684356878, 2684356808, 2684356738, 2684356668, 2684356598, 2684356528, 2684356458, 2684356388, 2684356318, 2684356248, 2684356178, 3221227579, 3221227578, 3221228000, 3221227999, 3221227998, 2684356948, 2684356878, 2684356808, 2684356738, 2684356668, 2684356598, 2684356528, 2684356458, 2684356388, 2684356318, 2684356248, 2684356948, 2684356878, 2684356808, 2684356738, 2684356668, 2684356598, 2684356528, 2684356458, 2684356388, 2684356318, 2684356668, 2684356598, 2684356528, 2684356458, 2684356388, 2684356318, 1610614282, 1610614352, 1610614422, 1610614492, 1610614562, 1610614632, 1610614702, 1610614772, 1610614842, 1610614282, 1610614352, 1610614422, 1610614492, 1610614562, 1610614632, 1610614702, 1610614772, 1610614842, 1610614912, 1967, 1967, 1967, 1967, 1967, 1967, 1967, 1967, 1967, 1967, 1967, 1967, 1967, 1967, 1967, 1967, 1967, 1967, 1967, 1967, 1967, 1967, 1967, 1967, 1616, 1617, 1618, 0, 0, 0, 0, 0, 0, 0, 0, 0, 0, 0, 0, 0, 0, 0, 0, 0, 0, 0, 0, 1896, 1897, 3221227509, 3221227508, 3221227930, 3221227929, 3221227928, 0, 0, 0, 0, 0, 0, 0, 0, 0, 0, 0, 0, 0, 0, 0, 0, 0, 0, 0, 0, 0, 0, 0, 0, 0, 0, 0, 0, 0, 0, 0, 0, 0, 0, 0, 0, 0, 0, 0, 0, 0, 0, 0, 0, 0, 0, 0, 0, 0, 0, 0, 0, 0, 0, 0, 0, 0, 0, 0, 0, 0, 0, 0, 0, 0, 0, 0, 0, 0, 0, 1686, 1687, 1688, 0, 0, 0, 0, 0, 0, 0, 0, 0, 0, 0, 0, 0, 0, 0, 0, 0, 0, 0, 0, 1966, 1967, 3221227439, 3221227438, 3221227860, 3221227859, 3221227858, 0, 0, 0, 0, 0, 0, 0, 0, 0, 0, 0, 0, 0, 0, 0, 0, 0, 0, 0, 0, 0, 0, 0, 0, 0, 0, 0, 0, 0, 0, 0, 0, 0, 0, 0, 0, 0, 0, 0, 0, 0, 0, 0, 0, 0, 0, 0, 0, 0, 0, 0, 0, 0, 0, 0, 0, 0, 0, 0, 0, 0, 0, 0, 0, 0, 0, 0, 0, 0, 0, 1756, 1757, 1758, 0, 0, 0, 0, 0, 0, 0, 0, 0, 0, 0, 0, 0, 0, 0, 0, 0, 0, 0, 0, 2036, 2037, 3221227369, 3221227368, 3221227790, 3221227789, 3221227788, 0, 0, 0, 0, 0, 0, 0, 0, 0, 0, 0, 0, 0, 0, 0, 0, 0, 0, 0, 0, 0, 0, 0, 0, 0, 0, 0, 0, 0, 0, 0, 0, 0, 0, 0, 0, 0, 0, 0, 0, 0, 0, 0, 0, 0, 0, 0, 0, 0, 0, 0, 0, 0, 0, 0, 0, 0, 0, 0, 0, 0, 0, 0, 0, 0, 0, 0, 0, 0, 0, 1826, 1827, 1828, 0, 0, 0, 0, 0, 0, 0, 0, 0, 0, 0, 0, 0, 0, 0, 0, 0, 0, 0, 0, 2106, 2107, 3221227299, 3221227298, 3221227720, 3221227719, 3221227718, 0, 0, 0, 0, 0, 0, 0, 0, 0, 0, 0, 0, 0, 0, 0, 0, 0, 0, 0, 0, 0, 0, 0, 0, 0, 0, 0, 0, 0, 0, 0, 0, 0, 0, 0, 0, 0, 0, 0, 0, 0, 0, 0, 0, 0, 0, 0, 0, 0, 0, 0, 0, 0, 0, 0, 0, 0, 0, 0, 0, 0, 0, 0, 0, 0, 0, 0, 0, 0, 0, 1616, 1617, 1618, 0, 0, 0, 0, 0, 0, 0, 0, 0, 0, 0, 0, 0, 0, 0, 0, 0, 0, 0, 0, 2176, 2177, 3221227229, 3221227228, 3221227650, 3221227649, 3221227648, 0, 0, 0, 0, 0, 0, 0, 0, 0, 0, 0, 0, 0, 0, 0, 0, 0, 0, 0, 0, 0, 0, 0, 0, 0, 0, 0, 0, 0, 0, 0, 0, 0, 0, 0, 0, 0, 0, 0, 0, 0, 0, 0, 0, 0, 0, 0, 0, 0, 0, 0, 0, 0, 0, 0, 0, 0, 0, 0, 0, 0, 0, 0, 0, 0, 0, 0, 0, 0, 0, 1686, 1687, 1688, 0, 0, 0, 0, 0, 0, 0, 0, 0, 0, 0, 0, 0, 0, 0, 0, 0, 0, 0, 0, 3221228070, 1616, 1617, 1618, 3221227580, 3221227579, 3221227578, 0, 0, 0, 0, 0, 0, 0, 0, 0, 0, 0, 0, 0, 0, 0, 0, 0, 0, 0, 0, 0, 0, 0, 0, 0, 0, 0, 0, 0, 0, 0, 0, 0, 0, 0, 0, 0, 0, 0, 0, 0, 0, 0, 0, 0, 0, 0, 0, 0, 0, 0, 0, 0, 0, 0, 0, 0, 0, 0, 0, 0, 0, 0, 0, 0, 0, 0, 0, 0, 0, 1756, 1757, 1758, 2684357156, 2684357086, 2684357016, 2684356946, 2684356876, 2684356806, 2684356736, 2684356666, 2684356596, 2684356526, 2684356456, 2684356386, 2684356316, 2684356246, 2684356176, 0, 0, 0, 0, 0, 3221228000, 1686, 1687, 1688, 3221227510, 3221227509, 3221227508, 0, 0, 0, 0, 0, 0, 0, 0, 0, 0, 0, 0, 0, 0, 0, 0, 0, 0, 0, 0, 0, 0, 0, 0, 0, 0, 0, 0, 0, 0, 0, 0, 0, 0, 0, 0, 0, 0, 0, 0, 0, 0, 0, 0, 0, 0, 0, 0, 0, 0, 0, 0, 0, 0, 0, 0, 0, 0, 0, 0, 2684356455, 2684356385, 2684356315, 2684356245, 2684356175, 3758098562, 3758098492, 3758098422, 3758098352, 3758098282, 3758098212, 1827, 1828, 2684357157, 2684357087, 2684357017, 2684356947, 2684356877, 2684356807, 2684356737, 2684356667, 2684356597, 2684356527, 2684356457, 2684356387, 2684356317, 2684356247, 2684356177, 0, 0, 0, 0, 0, 3221227930, 1756, 1757, 1758, 3221227440, 3221227439, 3221227438, 0, 0, 0, 0, 0, 0, 0, 0, 0, 0, 0, 0, 0, 0, 0, 0, 0, 0, 0, 0, 0, 0, 0, 0, 0, 0, 0, 0, 0, 0, 0, 0, 0, 0, 0, 0, 0, 0, 0, 0, 0, 0, 0, 0, 0, 0, 0, 0, 0, 0, 0, 0, 0, 0, 0, 0, 0, 0, 0, 0, 2684356456, 2684356386, 2684356316, 2684356246, 2684356176, 3758098561, 3758098491, 3758098421, 3758098351, 3758098281, 3758098211, 1897, 1898, 2684357158, 2684357088, 2684357018, 2684356948, 2684356878, 2684356808, 2684356738, 2684356668, 2684356598, 2684356528, 2684356458, 2684356388, 2684356318, 2684356248, 2684356178, 0, 0, 0, 0, 0, 3221227860, 1826, 1827, 1828, 3221228070, 3221228069, 3221228068, 0, 0, 0, 0, 0, 0, 0, 0, 0, 0, 0, 0, 0, 0, 0, 0, 0, 0, 0, 0, 0, 0, 0, 0, 0, 0, 0, 0, 0, 0, 0, 0, 0, 0, 0, 0, 0, 0, 0, 0, 0, 0, 0, 0, 0, 0, 0, 0, 0, 0, 0, 0, 0, 0, 0, 0, 0, 0, 0, 0, 2684356457, 2684356387, 2684356317, 2684356247, 2684356177, 3758098560, 3758098490, 3758098420, 3758098350, 3758098280, 3758098210, 1967, 1968, 0, 0, 0, 0, 0, 0, 0, 0, 0, 0, 0, 0, 0, 0, 0, 0, 0, 0, 0, 0, 3221227790, 1896, 1897, 1898, 3221228000, 3221227999, 3221227998, 0, 0, 0, 0, 0, 0, 0, 0, 0, 0, 0, 0, 0, 0, 0, 0, 0, 0, 0, 0, 0, 0, 0, 0, 0, 0, 0, 0, 0, 0, 0, 0, 0, 0, 0, 0, 0, 0, 0, 0, 0, 0, 0, 0, 0, 0, 0, 0, 0, 0, 0, 0, 0, 0, 0, 0, 0, 0, 0, 0, 0, 0, 0, 0, 0, 0, 0, 0, 0, 0, 0, 0, 0, 0, 0, 0, 0, 0, 0, 0, 0, 0, 0, 0, 0, 0, 0, 0, 0, 0, 0, 0, 0, 3221227720, 1966, 1967, 1968, 3221227930, 3221227929, 3221227928, 0, 0, 0, 0, 0, 0, 0, 0, 0, 0, 0, 0, 0, 0, 0, 0, 0, 0, 0, 0, 0, 0, 0, 0, 0, 0, 0, 0, 0, 0, 0, 0, 0, 0, 0, 0, 0, 0, 0, 0, 0, 0, 0, 0, 0, 0, 0, 0, 0, 0, 0, 0, 0, 0, 0, 0, 0, 0, 0, 0, 0, 0, 0, 0, 0, 0, 0, 0, 0, 0, 0, 0, 0, 0, 0, 0, 0, 0, 0, 0, 0, 0, 0, 0, 0, 0, 0, 0, 0, 0, 0, 0, 0, 3221227650, 2036, 2037, 2038, 3221227860, 3221227859, 3221227858, 0, 0, 0, 0, 0, 0, 0, 0, 0, 0, 0, 0, 0, 0, 0, 0, 0, 0, 0, 0, 0, 0, 0, 0, 0, 0, 0, 0, 0, 0, 0, 0, 0, 0, 0, 0, 0, 0, 0, 0, 0, 0, 0, 0, 0, 0, 0, 0, 0, 0, 0, 0, 0, 0, 0, 0, 0, 0, 0, 0, 0, 0, 0, 0, 0, 0, 0, 0, 0, 0, 0, 0, 0, 0, 0, 0, 0, 0, 0, 0, 0, 0, 0, 0, 0, 0, 0, 0, 0, 0, 0, 0, 0, 3221227580, 2106, 2107, 2108, 3221227790, 3221227789, 3221227788, 0, 0, 0, 0, 0, 0, 0, 0, 0, 0, 0, 0, 0, 0, 0, 0, 0, 0, 0, 0, 0, 0, 0, 0, 0, 0, 0, 0, 0, 0, 0, 0, 0, 0, 0, 0, 0, 0, 0, 0, 0, 0, 0, 0, 0, 0, 0, 0, 0, 0, 0, 0, 0, 0, 0, 0, 0, 0, 0, 0, 0, 0, 0, 0, 0, 0, 0, 0, 0, 0, 0, 0, 0, 0, 0, 0, 0, 0, 0, 0, 0, 0, 0, 0, 0, 0, 0, 0, 0, 0, 0, 0, 0, 3221227510, 2176, 2177, 2178, 3221227720, 3221227719, 3221227718, 0, 0, 0, 0, 0, 0, 0, 0, 0, 0, 0, 0, 0, 0, 0, 0, 0, 0, 0, 0, 0, 0, 0, 0, 0, 0, 0, 0, 0, 0, 0, 0, 0, 0, 0, 0, 0, 0, 0, 0, 0, 0, 0, 0, 0, 0, 0, 0, 0, 0, 0, 0, 0, 0, 0, 0, 0, 0, 0, 0, 0, 0, 0, 0, 0, 0, 0, 0, 0, 0, 0, 0, 0, 0, 0, 0, 0, 0, 0, 0, 0, 0, 0, 0, 0, 0, 0, 0, 0, 0, 0, 0, 0, 3221227440, 2246, 2247, 2248, 3221227650, 3221227649, 3221227648, 0, 0, 0, 0, 0, 0, 0, 0, 0, 0, 0, 0, 0, 0, 0, 0, 0, 0, 0, 0, 0, 0, 0, 0, 0, 0, 0, 0, 0, 0, 0, 0, 0, 0, 0, 0, 0, 0, 0, 0, 0, 0, 0, 0, 0, 0, 0, 0, 0, 0, 0, 0, 0, 0, 0, 0, 0, 0, 0, 0, 0, 0, 0, 0, 0, 0, 0, 0, 0, 0, 0, 0, 0, 0, 0, 0, 0, 0, 0, 0, 0, 0, 0, 0, 0, 0, 0, 0, 0, 0, 0, 0, 0, 3221227370, 2316, 2317, 2318, 3221227580, 3221227579, 3221227578, 0, 0, 0, 0, 0, 0, 0, 0, 2684357156, 2684357086, 2684357016, 2684356946, 2684356876, 2684356806, 2684356736, 2684356666, 2684356596, 2684356526, 2684356456, 2684356386, 2684356316, 2684356246, 2684356176, 2684356736, 2684356666, 2684356596, 2684356526, 2684356456, 2684356386, 2684356316, 2684356246, 2684356176, 2684357156, 2684357086, 2684357016, 2684356946, 2684356876, 2684356806, 2684356736, 2684356666, 2684356596, 2684356526, 2684356456, 2684356386, 2684356316, 2684356246, 2684356176, 2684357086, 2684357016, 2684356946, 2684356876, 2684356806, 2684356736, 2684356666, 2684356596, 2684356526, 2684356456, 2684356386, 2684356316, 2684356246, 2684356176, 2684357086, 2684357016, 2684356946, 2684356876, 2684356806, 2684356736, 2684356666, 2684356596, 2684356526, 2684356456, 2684356386, 2684356316, 2684356246, 2684356596, 2684356526, 2684356456, 2684356596, 2684356526, 2684356456, 2684356386, 2684356316, 2684357156, 2684357086, 2684357016, 2684356946, 2684356876, 2684356806, 2684356736, 2684356666, 2684356596, 2684356526, 2684356456, 2684356386, 2684356316, 2684356246, 2684356176, 3221227510, 3221227509, 3221227508, 0, 0, 0, 0, 0, 0, 0, 0, 2684357157, 2684357087, 2684357017, 2684356947, 2684356877, 2684356807, 2684356737, 2684356667, 2684356597, 2684356527, 2684356457, 2684356387, 2684356317, 2684356247, 2684356177, 2684356737, 2684356667, 2684356597, 2684356527, 2684356457, 2684356387, 2684356317, 2684356247, 2684356177, 2684357157, 2684357087, 2684357017, 2684356947, 2684356877, 2684356807, 2684356737, 2684356667, 2684356597, 2684356527, 2684356457, 2684356387, 2684356317, 2684356247, 2684356177, 2684357087, 2684357017, 2684356947, 2684356877, 2684356807, 2684356737, 2684356667, 2684356597, 2684356527, 2684356457, 2684356387, 2684356317, 2684356247, 2684356177, 2684357087, 2684357017, 2684356947, 2684356877, 2684356807, 2684356737, 2684356667, 2684356597, 2684356527, 2684356457, 2684356387, 2684356596, 2684356526, 2684356456, 2684356386, 2684356316, 2684356596, 2684356526, 2684356456, 2684356386, 2684356316, 2684357157, 2684357087, 2684357017, 2684356947, 2684356877, 2684356807, 2684356737, 2684356667, 2684356597, 2684356527, 2684356457, 2684356387, 2684356317, 2684356247, 2684356177, 3221227440, 3221227439, 3221227438, 0, 0, 0, 0, 0, 0, 0, 0, 2684357158, 2684357088, 2684357018, 2684356948, 2684356878, 2684356808, 2684356738, 2684356668, 2684356598, 2684356528, 2684356458, 2684356388, 2684356318, 2684356248, 2684356178, 2684356738, 2684356668, 2684356598, 2684356528, 2684356458, 2684356388, 2684356318, 2684356248, 2684356178, 2684357158, 2684357088, 2684357018, 2684356948, 2684356878, 2684356808, 2684356738, 2684356668, 2684356598, 2684356528, 2684356458, 2684356388, 2684356318, 2684356248, 2684356178, 2684357088, 2684357018, 2684356948, 2684356878, 2684356808, 2684356738, 2684356668, 2684356598, 2684356528, 2684356458, 2684356388, 2684356318, 2684356248, 2684356178, 2684357088, 2684357018, 2684356948, 2684356878, 2684356808, 2684356738, 2684356668, 2684356598, 2684356528, 2684356458, 2684356388, 2684356597, 2684356527, 2684356457, 2684356387, 2684356317, 2684356597, 2684356527, 2684356457, 2684356387, 2684356317, 2684357158, 2684357088, 2684357018, 2684356948, 2684356878, 2684356808, 2684356738, 2684356668, 2684356598, 2684356528, 2684356458, 2684356388, 2684356318, 2684356248, 2684356178, 3221227370, 3221227369, 3221227368, 0, 0, 0, 0, 0, 0, 0, 0, 2684357717, 2684357647, 2684357577, 2684357507, 2684357437, 2684357367, 2684357297, 2684357227, 2684357157, 2684357087, 2684357017, 2684357717, 2684357647, 2684357577, 2684357507, 2684357437, 2684357367, 2684357297, 2684357227, 2684357157, 2684357087, 2684357017, 2684356947, 2684356877, 2684356807, 2684356737, 2684356667, 2684356597, 2684356527, 2684357297, 2684357227, 2684357157, 2684357087, 2684357017, 2684356947, 2684356877, 2684356807, 2684356737, 2684356667, 2684356597, 2684356527, 2684357367, 2684357297, 2684357227, 2684357157, 2684357087, 2684357017, 2684356947, 2684356877, 2684356807, 2684356737, 2684356667, 2684356597, 2684356527, 2684357577, 2684357507, 2684357437, 2684357367, 2684357297, 2684357227, 2684357157, 2684357087, 2684357017, 2684356947, 2684356877, 2684356807, 2684356737, 2684356667, 2684356597, 2684356527, 2684357577, 2684357507, 2684357437, 2684357367, 2684357297, 2684357227, 2684357157, 2684357087, 2684357017, 2684356947, 2684356877, 2684356807, 2684356737, 2684356667, 2684356597, 2684356527, 2596, 2597, 2598, 3221227300, 3221227299, 3221227298, 0, 0, 0, 0, 0, 0, 0, 0, 0, 0, 0, 0, 0, 0, 0, 0, 0, 0, 0, 0, 0, 0, 0, 0, 0, 0, 0, 0, 0, 0, 0, 0, 0, 0, 0, 0, 0, 0, 0, 0, 0, 0, 0, 0, 0, 0, 0, 0, 0, 0, 0, 0, 0, 0, 0, 0, 0, 0, 0, 0, 0, 0, 0, 0, 0, 0, 0, 0, 0, 0, 0, 0, 0, 0, 0, 0, 0, 0, 0, 0, 0, 0, 0, 0, 0, 0, 0, 0, 0, 0, 0, 0, 0, 0, 0, 0, 0, 3221228070, 3221228069, 3221228068, 0, 0, 0, 0, 0, 0, 0, 0, 0, 0, 0, 0, 0, 0, 0, 0, 0, 0, 0, 0, 0, 0, 0, 0, 0, 0, 0, 0, 0, 0, 0, 0, 0, 0, 0, 0, 0, 0, 0, 0, 0, 0, 0, 0, 0, 0, 0, 0, 0, 0, 0, 0, 0, 0, 0, 0, 0, 0, 0, 0, 0, 0, 0, 0, 0, 0, 0, 0, 0, 0, 0, 0, 0, 0, 0, 0, 0, 0, 0, 0, 0, 0, 0, 0, 0, 0, 0, 0, 0, 0, 0, 0, 0, 0, 0, 0, 0, 3221228000, 3221227999, 3221227998, 0, 0, 0, 0, 0, 0, 0, 0, 0, 0, 0, 0, 0, 0, 0, 0, 0, 0, 0, 0, 0, 0, 0, 0, 0, 0, 0, 0, 0, 0, 0, 0, 0, 0, 0, 0, 0, 0, 0, 0, 0, 0, 0, 0, 0, 0, 0, 0, 0, 0, 0, 0, 0, 0, 0, 0, 0, 0, 0, 0, 0, 0, 0, 0, 0, 0, 0, 0, 0, 0, 0, 0, 0, 0, 0, 0, 0, 0, 0, 0, 0, 0, 0, 0, 0, 0, 0, 0, 0, 0, 0, 0, 0, 0, 0, 0, 0, 3221227930, 3221227929, 3221227928, 0, 0, 0, 0, 0, 0, 0, 0, 0, 0, 0, 0, 0, 0, 0, 0, 0, 0, 0, 0, 0, 0, 0, 0, 0, 0, 0, 0, 0, 0, 0, 0, 0, 0, 0, 0, 0, 0, 0, 0, 0, 0, 0, 0, 0, 0, 0, 0, 0, 0, 0, 0, 0, 0, 0, 0, 0, 0, 0, 0, 0, 0, 0, 0, 0, 0, 0, 0, 0, 0, 0, 0, 0, 0, 0, 0, 0, 0, 0, 0, 0, 0, 0, 0, 0, 0, 0, 0, 0, 0, 0, 0, 0, 0, 0, 0, 0, 3221228070, 3221228069, 3221228068, 0, 0, 0, 0, 0, 0, 0, 0, 0, 0, 0, 0, 0, 0, 0, 0, 0, 0, 0, 0, 0, 0, 0, 0, 0, 0, 0, 0, 0, 0, 0, 0, 0, 0, 0, 0, 0, 0, 0, 0, 0, 0, 0, 0, 0, 0, 0, 0, 0, 0, 0, 0, 0, 0, 0, 0, 0, 0, 0, 0, 0, 0, 0, 0, 0, 0, 0, 0, 0, 0, 0, 0, 0, 0, 0, 0, 0, 0, 0, 0, 0, 0, 0, 0, 0, 0, 0, 0, 0, 0, 0, 0, 0, 0, 0, 0, 0, 3221228000, 3221227999, 3221227998, 0, 0, 0, 0, 0, 0, 0, 0, 0, 0, 0, 0, 0, 0, 0, 0, 0, 0, 0, 0, 0, 0, 0, 0, 0, 0, 0, 0, 0, 0, 0, 0, 0, 0, 0, 0, 0, 0, 0, 0, 0, 0, 0, 0, 0, 0, 0, 0, 0, 0, 0, 0, 0, 0, 0, 0, 0, 0, 0, 0, 0, 0, 0, 0, 0, 0, 0, 0, 0, 0, 0, 0, 0, 0, 0, 0, 0, 0, 0, 0, 0, 0, 0, 0, 0, 0, 0, 0, 0, 0, 0, 0, 0, 0, 0, 0, 0, 3221227930, 3221227929, 3221227928, 0, 0, 0, 0, 0, 0, 0, 0, 0, 0, 0, 0, 0, 0, 0, 0, 0, 0, 0, 0, 0, 0, 0, 0, 0, 0, 0, 0, 0, 0, 0, 0, 0, 0, 0, 0, 0, 0, 0, 0, 0, 0, 0, 0, 0, 0, 0, 0, 0, 0, 0, 0, 0, 0, 0, 0, 0, 0, 0, 0, 0, 0, 0, 0, 0, 0, 0, 0, 0, 0, 0, 0, 0, 0, 0, 0, 0, 0, 0, 0, 0, 0, 0, 0, 0, 0, 0, 0, 0, 0, 0, 0, 0, 0, 0, 0, 0, 1610614354, 1610614424, 1610614494, 3758098982, 3758098912, 3758098842, 3758098772, 3758098702, 3758098632, 3758098562, 3758098492, 3758098422, 3758098352, 3758098282, 3758098212, 3758098142, 3758098072, 3758098002, 0, 0, 0, 0, 0, 0, 0, 0, 0, 0, 0, 0, 2684356736, 2684356666, 2684356596, 2684356526, 2684356456, 2684356386, 2684356316, 2684356246, 2684356736, 2684356666, 2684356596, 2684356526, 2684356456, 2684356736, 2684356736, 2684356666, 2684356596, 2684356526, 2684356456, 2684356386, 2684356316, 2684356246, 0, 0, 0, 0, 0, 0, 0, 0, 0, 0, 0, 0, 0, 0, 0, 0, 0, 0, 2684356736, 2684356666, 2684356596, 2684356526, 2684356456, 2684356386, 2684356316, 2684356736, 2684356666, 2684356596, 2684356526, 2684356456, 2684356736, 2684356666, 2684356596, 2684356526, 2684356456, 2684356386, 2684356316, 2684356246, 0, 0, 0, 0, 0, 0, 0, 0, 0, 0, 1610614353, 1610614423, 1610614493, 3758098981, 3758098911, 3758098841, 3758098771, 3758098701, 3758098631, 3758098561, 3758098491, 3758098421, 3758098351, 3758098281, 3758098211, 3758098141, 3758098071, 3758098001, 0, 0, 0, 0, 0, 0, 0, 0, 0, 0, 0, 0, 2684356737, 2684356667, 2684356597, 2684356527, 2684356457, 2684356387, 2684356317, 2684356247, 2684356737, 2684356667, 2684356597, 2684356527, 2684356457, 2684356737, 2684356737, 2684356667, 2684356597, 2684356527, 2684356457, 2684356387, 2684356317, 2684356247, 0, 0, 0, 0, 0, 0, 0, 0, 0, 0, 0, 0, 0, 0, 0, 0, 0, 0, 2684356737, 2684356667, 2684356597, 2684356527, 2684356457, 2684356387, 2684356317, 2684356737, 2684356667, 2684356597, 2684356527, 2684356457, 2684356737, 2684356667, 2684356597, 2684356527, 2684356457, 2684356387, 2684356317, 2684356247, 0, 0, 0, 0, 0, 0, 0, 0, 0, 0, 1610614352, 1610614422, 1610614492, 3758098980, 3758098910, 3758098840, 3758098770, 3758098700, 3758098630, 3758098560, 3758098490, 3758098420, 3758098350, 3758098280, 3758098210, 3758098140, 3758098070, 3758098000, 0, 0, 0, 0, 0, 0, 0, 0, 0, 0, 0, 0, 2684356738, 2684356668, 2684356598, 2684356528, 2684356458, 2684356388, 2684356318, 2684356248, 2684356738, 2684356668, 2684356598, 2684356528, 2684356458, 2684356738, 2684356738, 2684356668, 2684356598, 2684356528, 2684356458, 2684356388, 2684356318, 2684356248, 0, 0, 0, 0, 0, 0, 0, 0, 0, 0, 0, 0, 0, 0, 0, 0, 0, 0, 2684356738, 2684356668, 2684356598, 2684356528, 2684356458, 2684356388, 2684356318, 2684356738, 2684356668, 2684356598, 2684356528, 2684356458, 2684356738, 2684356668, 2684356598, 2684356528, 2684356458, 2684356388, 2684356318, 2684356248, 0, 0, 0, 0, 0, 0, 0, 0, 0, 0, 3758098842, 3758098772, 3758098702, 3758098632, 3758098562, 3758098492, 3758098422, 3758098352, 3758098282, 3758098212, 3758098142, 3758098072, 3758098002, 1757, 1758, 0, 0, 0, 0, 0, 0, 0, 0, 0, 0, 0, 0, 0, 0, 0, 0, 0, 0, 1686, 1687, 1688, 2684356736, 2684356666, 2684356736, 2684356666, 2684356596, 2684356526, 2684356456, 2684356386, 2684356316, 2684356246, 1686, 1687, 1688, 0, 0, 0, 0, 0, 0, 0, 0, 0, 0, 0, 0, 0, 0, 0, 0, 0, 0, 0, 0, 0, 0, 0, 0, 0, 0, 1686, 1687, 1073744000, 1073744001, 1073744002, 3221227650, 1073744000, 1073744001, 1073744002, 1073744000, 1073744001, 1073744002, 3221227650, 3221227649, 3221227648, 0, 0, 0, 0, 0, 0, 0, 0, 0, 0, 3758098841, 3758098771, 3758098701, 3758098631, 3758098561, 3758098491, 3758098421, 3758098351, 3758098281, 3758098211, 3758098141, 3758098071, 3758098001, 1827, 1828, 0, 0, 0, 0, 0, 0, 0, 0, 0, 0, 0, 0, 0, 0, 0, 0, 0, 0, 1756, 1757, 1758, 2684356737, 2684356667, 2684356737, 2684356667, 2684356597, 2684356527, 2684356457, 2684356387, 2684356317, 2684356247, 1756, 1757, 1758, 0, 0, 0, 0, 0, 0, 0, 0, 0, 0, 0, 0, 0, 0, 0, 0, 0, 0, 0, 0, 0, 0, 0, 0, 0, 0, 1756, 1757, 1073743930, 1073743931, 1073743932, 3221227580, 1073743930, 1073743931, 1073743932, 1073743930, 1073743931, 1073743932, 3221227580, 3221227579, 3221227578, 0, 0, 0, 0, 0, 0, 0, 0, 0, 0, 3758098842, 3758098772, 3758098702, 3758098632, 3758098562, 3758098492, 3758098422, 3758098352, 3758098282, 3758098212, 3758098142, 3758098072, 3758098002, 1897, 1898, 0, 0, 0, 0, 0, 0, 0, 0, 0, 0, 0, 0, 0, 0, 0, 0, 0, 0, 1826, 1827, 1828, 2684356738, 2684356668, 2684356736, 2684356666, 2684356596, 2684356526, 2684356456, 2684356386, 2684356316, 2684356246, 1826, 1827, 1828, 0, 0, 0, 0, 0, 0, 0, 0, 0, 0, 0, 0, 0, 0, 0, 0, 0, 0, 0, 0, 0, 0, 0, 0, 0, 0, 1826, 1827, 1073743860, 1073743861, 1073743862, 3221227510, 1073743860, 1073743861, 1073743862, 1073743860, 1073743861, 1073743862, 3221227510, 3221227509, 536872598, 536872668, 536872738, 536872598, 536872668, 536872738, 536872808, 536872878, 536872948, 536873018, 536873088, 3758098841, 3758098771, 3758098701, 3758098631, 3758098561, 3758098491, 3758098421, 3758098351, 3758098281, 3758098211, 3758098141, 3758098071, 3758098001, 1967, 1968, 0, 0, 0, 0, 0, 0, 0, 0, 0, 0, 0, 0, 0, 0, 0, 0, 0, 0, 1896, 2684356736, 2684356666, 2684356596, 2684356526, 2684356456, 2684356386, 2684356316, 2684356246, 2684356457, 2684356387, 2684356317, 2684356247, 1896, 1897, 1898, 0, 0, 0, 0, 0, 0, 0, 0, 0, 0, 0, 0, 0, 0, 0, 0, 0, 0, 0, 0, 0, 0, 0, 0, 0, 0, 1896, 1897, 1073743790, 1073743791, 1073743792, 3221227440, 1073743790, 1073743791, 1073743792, 1073743790, 1073743791, 1073743792, 3221227440, 3221227439, 536872599, 536872669, 536872739, 536872599, 536872669, 536872739, 536872809, 536872879, 536872949, 536873019, 536873089, 3758098840, 3758098770, 3758098700, 3758098630, 3758098560, 3758098490, 3758098420, 3758098350, 3758098280, 3758098210, 3758098140, 3758098070, 3758098000, 2037, 2038, 0, 0, 0, 0, 0, 0, 0, 0, 0, 0, 0, 0, 0, 0, 0, 0, 0, 0, 1966, 2684356737, 2684356667, 2684356597, 2684356527, 2684356457, 2684356387, 2684356317, 2684356247, 2684356458, 2684356388, 2684356318, 2684356248, 1966, 1967, 1968, 0, 0, 0, 0, 0, 0, 0, 0, 0, 0, 0, 0, 0, 0, 0, 0, 0, 0, 0, 0, 0, 0, 0, 0, 0, 0, 1966, 1967, 1073743720, 1073743721, 1073743722, 3221227370, 1073743720, 1073743721, 1073743722, 1073743720, 1073743721, 1073743722, 3221227370, 3221227369, 536872598, 536872668, 536872738, 536872600, 536872670, 536872740, 536872810, 536872880, 536872950, 536873020, 536873090, 536872598, 536872668, 536872738, 536872808, 536872878, 536872948, 536873018, 536873088, 536873158, 536873228, 536873298, 536873368, 536873438, 536873508, 2108, 0, 0, 0, 0, 0, 0, 0, 0, 0, 0, 0, 0, 0, 0, 0, 0, 0, 0, 2036, 2684356738, 1610614424, 1610614494, 1610614564, 1610614424, 1610614494, 1610614564, 1610614634, 1610614704, 1610614774, 1610614844, 1610614914, 2036, 2037, 2038, 0, 0, 0, 0, 0, 0, 0, 0, 0, 0, 0, 0, 0, 0, 0, 0, 0, 0, 0, 0, 0, 0, 0, 0, 0, 0, 2036, 2037, 1073743650, 1073743651, 1073743652, 3221227300, 1073743650, 1073743651, 1073743652, 1073743650, 1073743651, 1073743652, 3221227300, 3221227299, 536872599, 536872669, 536872739, 536872809, 536872598, 536872668, 536872738, 536872808, 536872878, 536872948, 536873018, 536872599, 536872669, 536872739, 536872809, 536872879, 536872949, 536873019, 536873089, 536873159, 536873229, 536873299, 536873369, 536873439, 536873509, 2178, 0, 0, 0, 0, 0, 0, 0, 0, 0, 0, 0, 0, 0, 0, 0, 0, 0, 0, 1610614424, 1610614494, 1610614564, 1610614634, 1610614704, 1610614774, 1610614844, 1610614424, 1610614494, 1610614564, 1610614634, 1610614704, 1610614774, 1610614844, 1610614914, 2108, 0, 0, 0, 0, 0, 0, 0, 0, 0, 0, 0, 0, 0, 0, 0, 0, 0, 0, 0, 0, 0, 0, 0, 0, 0, 0, 2106, 2107, 1073743580, 1073743581, 1073743582, 3221227230, 1073743580, 1073743581, 1073743582, 1073743580, 1073743581, 1073743582, 3221227230, 3221227229, 536872598, 536872668, 536872738, 536872808, 536872599, 536872669, 536872739, 536872809, 536872879, 536872949, 536873019, 536872600, 536872670, 536872740, 536872810, 536872880, 536872950, 536873020, 536873090, 536873160, 536873230, 536873300, 536873370, 536873440, 536873510, 2248, 0, 0, 0, 0, 0, 0, 0, 0, 0, 0, 0, 0, 0, 0, 0, 0, 0, 0, 1610614423, 1610614493, 1610614563, 1610614633, 1610614703, 1610614773, 1610614843, 1610614423, 1610614493, 1610614563, 1610614633, 1610614703, 1610614773, 1610614843, 1610614913, 2178, 0, 0, 0, 0, 0, 0, 0, 0, 0, 0, 0, 0, 0, 0, 0, 0, 0, 0, 0, 0, 0, 0, 0, 0, 0, 0, 2176, 2177, 1073743510, 1073743511, 1073743512, 3221227160, 1073743510, 1073743511, 1073743512, 1073743510, 1073743511, 1073743512, 3221227160, 3221227159, 536872599, 536872669, 536872739, 536872809, 536872600, 536872670, 536872740, 536872810, 536872880, 536872950, 536873020, 3221227090, 3221227089, 3221227088, 1967, 1967, 1967, 1967, 1967, 1967, 1967, 1967, 1967, 2316, 1610614424, 1610614494, 1610614564, 1610614634, 1610614704, 1610614774, 1610614844, 1610614914, 1967, 1610614424, 1610614494, 1610614564, 1610614424, 1610614494, 1610614564, 1610614634, 1610614704, 1610614774, 1610614844, 1610614914, 1610614422, 1610614492, 1610614562, 1610614632, 1610614702, 1610614772, 1610614842, 1610614422, 1610614492, 1610614562, 1610614632, 1610614702, 1610614772, 1610614842, 1610614912, 1967, 1610614424, 1610614494, 1610614564, 1610614634, 1610614704, 1610614774, 1610614844, 1610614914, 1967, 1610614424, 1610614494, 1610614564, 1610614634, 1610614704, 1610614774, 1610614844, 1610614914, 1610614424, 1610614494, 1610614564, 1610614634, 1610614704, 1610614774, 1610614844, 1610614914, 1610614424, 1610614494, 1610614564, 1610614634, 1610614704, 1610614774, 1610614844, 1610614914, 1967, 1967, 1967, 1967, 1967, 1967, 1967, 536872600, 536872670, 536872740, 536872810, 536872880, 536872950, 536873020, 536873090, 1967, 1967, 1967],
         "height":79,
         "name":"Collision Layer",
         "opacity":1,
         "type":"tilelayer",
         "visible":true,
         "width":100,
         "x":0,
         "y":0
        }],
 "nextobjectid":61,
 "orientation":"orthogonal",
 "renderorder":"right-down",
 "tiledversion":"1.1.5",
 "tileheight":32,
 "tilesets":[
        {
         "columns":70,
         "firstgid":1,
         "image":"CoralReefPlantsPNG\/coralReefTilesetFin.png",
         "imageheight":2240,
         "imagewidth":2240,
         "margin":0,
         "name":"coralReefTilesetFin",
         "spacing":0,
         "tilecount":4900,
         "tileheight":32,
         "tilewidth":32
        }],
 "tilewidth":32,
 "type":"map",
 "version":1,
 "width":100
}